q.py
q-2.7.dist-info/LICENSE
q-2.7.dist-info/METADATA
q-2.7.dist-info/WHEEL
q-2.7.dist-info/top_level.txt
q-2.7.dist-info/RECORD
